[
  {
    "id": "d16ced97-0e01-4881-a1b0-299a3ec45f29",
    "taskName": "desktop_runtime_manual:login",
    "displayName": "Login",
    "group": "Construction",
    "payload": {},
    "priority": 0,
    "status": "Succeeded",
    "retries": 0,
    "maxRetries": 0,
    "isRuntimeOnly": true,
    "nextAttemptAt": "2026-05-27T13:14:52.0932714+00:00",
    "createdAt": "2026-05-27T13:14:52.0784673+00:00",
    "updatedAt": "2026-05-27T13:15:02.5192938+00:00"
  },
  {
    "id": "ac2e0447-2b65-4825-8e7c-c0444fbce766",
    "taskName": "construct_building",
    "displayName": null,
    "group": "Construction",
    "payload": {
      "building_construct_slot_id": "39",
      "building_construct_gid": "16",
      "building_construct_name": "Rally Point",
      "target_village_name": "village2",
      "target_village_url": "dorf1.php?newdid=25050"
    },
    "priority": 0,
    "status": "Pending",
    "retries": 0,
    "maxRetries": 3,
    "isRuntimeOnly": false,
    "nextAttemptAt": "2026-05-27T13:15:08.1769626+00:00",
    "createdAt": "2026-05-27T13:15:08.1769626+00:00",
    "updatedAt": "2026-05-27T13:15:08.1769626+00:00"
  },
  {
    "id": "f7a1f420-a0cc-47db-898d-edd88377f998",
    "taskName": "construct_building",
    "displayName": null,
    "group": "Construction",
    "payload": {
      "building_construct_slot_id": "40",
      "building_construct_gid": "32",
      "building_construct_name": "Earth Wall",
      "target_village_name": "village2",
      "target_village_url": "dorf1.php?newdid=25050"
    },
    "priority": 0,
    "status": "Pending",
    "retries": 0,
    "maxRetries": 3,
    "isRuntimeOnly": false,
    "nextAttemptAt": "2026-05-27T13:15:19.9388303+00:00",
    "createdAt": "2026-05-27T13:15:19.9388303+00:00",
    "updatedAt": "2026-05-27T13:15:19.9388303+00:00"
  }
]